{
  "resourceType": "Bundle",
  "id": "Lucille-Blankenship-Holder-2646-Encounter-529",
  "type": "transaction",
  "entry": [
    {
      "fullUrl": "http://localhost:8080/cqf-ruler/baseDstu3/Encounter/Encounter-529",
      "resource": {
        "resourceType": "Encounter",
        "id": "Encounter-529",
        "meta": {
          "profile": [
            "http://hl7.org/fhir/us/hedis/StructureDefinition/hedis-encounter"
          ]
        },
        "extension": [
          {
            "url": "http://mihin.org/extension/copyright",
            "valueString": "Copyright 2014-2019 Michigan Health Information Network Shared Services. Licensed under the Apache License, Version 2.0 (the 'License'); you may not use this file except in compliance with the License. You may obtain a copy of the License at  http://www.apache.org/licenses/LICENSE-2.0.  Unless required by applicable law or agreed to in writing, software distributed under the License is distributed on an 'AS IS' BASIS, WITHOUT WARRANTIES OR CONDITIONS OF ANY KIND, either express or implied. See the License for the specific language governing permissions and limitations under the License."
          }
        ],
        "status": "finished",
        "class": {
          "system": "http://hl7.org/fhir/encounter-class",
          "code": "outpatient",
          "display": "outpatient"
        },
        "type": [
          {
            "coding": [
              {
                "system": "http://snomed.info/sct",
                "code": "170258001",
                "display": "Wellness Visit"
              }
            ]
          }
        ],
        "subject": {
          "reference": "Patient/Patient-2646",
          "display": "Lucille Blankenship Holder"
        },
        "participant": [
          {
            "period": {
              "start": "2017-11-26T06:00:00-05:00",
              "end": "2017-12-01T00:00:00-05:00"
            },
            "individual": {
              "reference": "Practitioner/Practitioner-2573",
              "display": "Leona Delgado Mathews MD"
            }
          }
        ],
        "period": {
          "start": "2017-11-26T06:00:00-05:00",
          "end": "2017-12-01T00:00:00-05:00"
        },
        "location": [
          {
            "location": {
              "reference": "Location/Location-265",
              "display": "Rush Healthcare"
            }
          }
        ],
        "serviceProvider": {
          "reference": "Organization/Organization-1102",
          "display": "Rush Healthcare"
        }
      },
      "request": {
        "method": "PUT",
        "url": "http://localhost:8080/cqf-ruler/baseDstu3/Encounter/Encounter-529"
      }
    },
    {
      "fullUrl": "http://localhost:8080/cqf-ruler/baseDstu3/Immunization/Immunization-48448",
      "resource": {
        "resourceType": "Immunization",
        "id": "Immunization-48448",
        "extension": [
          {
            "url": "http://mihin.org/extension/copyright",
            "valueString": "Copyright 2014-2019 Michigan Health Information Network Shared Services. Licensed under the Apache License, Version 2.0 (the 'License'); you may not use this file except in compliance with the License. You may obtain a copy of the License at  http://www.apache.org/licenses/LICENSE-2.0.  Unless required by applicable law or agreed to in writing, software distributed under the License is distributed on an 'AS IS' BASIS, WITHOUT WARRANTIES OR CONDITIONS OF ANY KIND, either express or implied. See the License for the specific language governing permissions and limitations under the License."
          }
        ],
        "identifier": [
          {
            "use": "official",
            "system": "mihin.org/fhir/sid/elementId",
            "value": "14957c99-b66f-44fa-b7b6-91134e10cf3a"
          }
        ],
        "status": "completed",
        "notGiven": false,
        "vaccineCode": {
          "coding": [
            {
              "system": "http://hl7.org/fhir/sid/cvx",
              "code": "140",
              "display": "Influenza, seasonal, injectable, preservative free"
            }
          ]
        },
        "patient": {
          "reference": "Patient/Patient-2646",
          "display": "Lucille Blankenship Holder"
        },
        "date": "2017-11-26T06:00:00-05:00",
        "primarySource": true,
        "location": {
          "reference": "Location/Location-265",
          "display": "Rush Healthcare"
        },
        "practitioner": [
          {
            "actor": {
              "reference": "Practitioner/Practitioner-2573",
              "display": "Leona Delgado Mathews MD"
            }
          }
        ]
      },
      "request": {
        "method": "PUT",
        "url": "http://localhost:8080/cqf-ruler/baseDstu3/Immunization/Immunization-48448"
      }
    },
    {
      "fullUrl": "http://localhost:8080/cqf-ruler/baseDstu3/Observation/Observation-65094",
      "resource": {
        "resourceType": "Observation",
        "id": "Observation-65094",
        "meta": {
          "profile": [
            "http://hl7.org/fhir/us/hedis/StructureDefinition/hedis-observation"
          ]
        },
        "extension": [
          {
            "url": "http://mihin.org/extension/copyright",
            "valueString": "Copyright 2014-2019 Michigan Health Information Network Shared Services. Licensed under the Apache License, Version 2.0 (the 'License'); you may not use this file except in compliance with the License. You may obtain a copy of the License at  http://www.apache.org/licenses/LICENSE-2.0.  Unless required by applicable law or agreed to in writing, software distributed under the License is distributed on an 'AS IS' BASIS, WITHOUT WARRANTIES OR CONDITIONS OF ANY KIND, either express or implied. See the License for the specific language governing permissions and limitations under the License."
          }
        ],
        "identifier": [
          {
            "use": "official",
            "system": "mihin.org/fhir/sid/elementId",
            "value": "dc7ade02-53f4-4b8e-a752-9191845ead32"
          }
        ],
        "status": "final",
        "category": [
          {
            "coding": [
              {
                "system": "http://hl7.org/fhir/observation-category",
                "code": "vital-signs",
                "display": "Vital Signs"
              }
            ]
          }
        ],
        "code": {
          "coding": [
            {
              "system": "http://loinc.org",
              "code": "8302-2",
              "display": "Body Height"
            }
          ]
        },
        "subject": {
          "reference": "Patient/Patient-2646",
          "display": "Lucille Blankenship Holder"
        },
        "context": {
          "reference": "Encounter/Encounter-529",
          "display": "Wellness Visit"
        },
        "effectiveDateTime": "2017-12-01T00:00:00-05:00",
        "performer": [
          {
            "reference": "Practitioner/Practitioner-2573",
            "display": "Leona Delgado Mathews MD"
          }
        ],
        "valueQuantity": {
          "value": 94,
          "unit": "cm"
        }
      },
      "request": {
        "method": "PUT",
        "url": "http://localhost:8080/cqf-ruler/baseDstu3/Observation/Observation-65094"
      }
    },
    {
      "fullUrl": "http://localhost:8080/cqf-ruler/baseDstu3/Observation/Observation-65095",
      "resource": {
        "resourceType": "Observation",
        "id": "Observation-65095",
        "meta": {
          "profile": [
            "http://hl7.org/fhir/us/hedis/StructureDefinition/hedis-observation"
          ]
        },
        "extension": [
          {
            "url": "http://mihin.org/extension/copyright",
            "valueString": "Copyright 2014-2019 Michigan Health Information Network Shared Services. Licensed under the Apache License, Version 2.0 (the 'License'); you may not use this file except in compliance with the License. You may obtain a copy of the License at  http://www.apache.org/licenses/LICENSE-2.0.  Unless required by applicable law or agreed to in writing, software distributed under the License is distributed on an 'AS IS' BASIS, WITHOUT WARRANTIES OR CONDITIONS OF ANY KIND, either express or implied. See the License for the specific language governing permissions and limitations under the License."
          }
        ],
        "identifier": [
          {
            "use": "official",
            "system": "mihin.org/fhir/sid/elementId",
            "value": "449bb048-464c-4e01-9b4c-67df4771288d"
          }
        ],
        "status": "final",
        "category": [
          {
            "coding": [
              {
                "system": "http://hl7.org/fhir/observation-category",
                "code": "vital-signs",
                "display": "Vital Signs"
              }
            ]
          }
        ],
        "code": {
          "coding": [
            {
              "system": "http://loinc.org",
              "code": "29463-7",
              "display": "Body Weight"
            }
          ]
        },
        "subject": {
          "reference": "Patient/Patient-2646",
          "display": "Lucille Blankenship Holder"
        },
        "context": {
          "reference": "Encounter/Encounter-529",
          "display": "Wellness Visit"
        },
        "effectiveDateTime": "2017-12-01T00:00:00-05:00",
        "performer": [
          {
            "reference": "Practitioner/Practitioner-2573",
            "display": "Leona Delgado Mathews MD"
          }
        ],
        "valueQuantity": {
          "value": 15.0,
          "unit": "kg"
        }
      },
      "request": {
        "method": "PUT",
        "url": "http://localhost:8080/cqf-ruler/baseDstu3/Observation/Observation-65095"
      }
    },
    {
      "fullUrl": "http://localhost:8080/cqf-ruler/baseDstu3/Observation/Observation-65096",
      "resource": {
        "resourceType": "Observation",
        "id": "Observation-65096",
        "meta": {
          "profile": [
            "http://hl7.org/fhir/us/hedis/StructureDefinition/hedis-observation"
          ]
        },
        "extension": [
          {
            "url": "http://mihin.org/extension/copyright",
            "valueString": "Copyright 2014-2019 Michigan Health Information Network Shared Services. Licensed under the Apache License, Version 2.0 (the 'License'); you may not use this file except in compliance with the License. You may obtain a copy of the License at  http://www.apache.org/licenses/LICENSE-2.0.  Unless required by applicable law or agreed to in writing, software distributed under the License is distributed on an 'AS IS' BASIS, WITHOUT WARRANTIES OR CONDITIONS OF ANY KIND, either express or implied. See the License for the specific language governing permissions and limitations under the License."
          }
        ],
        "identifier": [
          {
            "use": "official",
            "system": "mihin.org/fhir/sid/elementId",
            "value": "37a3ab3d-ec42-4ce4-bf5f-62920e707fc8"
          }
        ],
        "status": "final",
        "category": [
          {
            "coding": [
              {
                "system": "http://hl7.org/fhir/observation-category",
                "code": "vital-signs",
                "display": "Vital Signs"
              }
            ]
          }
        ],
        "code": {
          "coding": [
            {
              "system": "http://loinc.org",
              "code": "39156-5",
              "display": "Body Mass Index"
            }
          ]
        },
        "subject": {
          "reference": "Patient/Patient-2646",
          "display": "Lucille Blankenship Holder"
        },
        "context": {
          "reference": "Encounter/Encounter-529",
          "display": "Wellness Visit"
        },
        "effectiveDateTime": "2017-12-01T00:00:00-05:00",
        "performer": [
          {
            "reference": "Practitioner/Practitioner-2573",
            "display": "Leona Delgado Mathews MD"
          }
        ],
        "valueQuantity": {
          "value": 17.1,
          "unit": "kg/m2"
        }
      },
      "request": {
        "method": "PUT",
        "url": "http://localhost:8080/cqf-ruler/baseDstu3/Observation/Observation-65096"
      }
    },
    {
      "fullUrl": "http://localhost:8080/cqf-ruler/baseDstu3/Observation/Observation-65097",
      "resource": {
        "resourceType": "Observation",
        "id": "Observation-65097",
        "meta": {
          "profile": [
            "http://hl7.org/fhir/us/hedis/StructureDefinition/hedis-observation"
          ]
        },
        "extension": [
          {
            "url": "http://mihin.org/extension/copyright",
            "valueString": "Copyright 2014-2019 Michigan Health Information Network Shared Services. Licensed under the Apache License, Version 2.0 (the 'License'); you may not use this file except in compliance with the License. You may obtain a copy of the License at  http://www.apache.org/licenses/LICENSE-2.0.  Unless required by applicable law or agreed to in writing, software distributed under the License is distributed on an 'AS IS' BASIS, WITHOUT WARRANTIES OR CONDITIONS OF ANY KIND, either express or implied. See the License for the specific language governing permissions and limitations under the License."
          }
        ],
        "identifier": [
          {
            "use": "official",
            "system": "mihin.org/fhir/sid/elementId",
            "value": "f2496a9b-9fcb-44fc-afe7-835824089a83"
          }
        ],
        "status": "final",
        "category": [
          {
            "coding": [
              {
                "system": "http://hl7.org/fhir/observation-category",
                "code": "vital-signs",
                "display": "Vital Signs"
              }
            ]
          }
        ],
        "code": {
          "coding": [
            {
              "system": "http://loinc.org",
              "code": "8480-6",
              "display": "Systolic Blood Pressure"
            }
          ]
        },
        "subject": {
          "reference": "Patient/Patient-2646",
          "display": "Lucille Blankenship Holder"
        },
        "context": {
          "reference": "Encounter/Encounter-529",
          "display": "Wellness Visit"
        },
        "effectiveDateTime": "2017-12-01T00:00:00-05:00",
        "performer": [
          {
            "reference": "Practitioner/Practitioner-2573",
            "display": "Leona Delgado Mathews MD"
          }
        ],
        "valueQuantity": {
          "value": 132,
          "unit": "mmHg"
        }
      },
      "request": {
        "method": "PUT",
        "url": "http://localhost:8080/cqf-ruler/baseDstu3/Observation/Observation-65097"
      }
    },
    {
      "fullUrl": "http://localhost:8080/cqf-ruler/baseDstu3/Observation/Observation-65098",
      "resource": {
        "resourceType": "Observation",
        "id": "Observation-65098",
        "meta": {
          "profile": [
            "http://hl7.org/fhir/us/hedis/StructureDefinition/hedis-observation"
          ]
        },
        "extension": [
          {
            "url": "http://mihin.org/extension/copyright",
            "valueString": "Copyright 2014-2019 Michigan Health Information Network Shared Services. Licensed under the Apache License, Version 2.0 (the 'License'); you may not use this file except in compliance with the License. You may obtain a copy of the License at  http://www.apache.org/licenses/LICENSE-2.0.  Unless required by applicable law or agreed to in writing, software distributed under the License is distributed on an 'AS IS' BASIS, WITHOUT WARRANTIES OR CONDITIONS OF ANY KIND, either express or implied. See the License for the specific language governing permissions and limitations under the License."
          }
        ],
        "identifier": [
          {
            "use": "official",
            "system": "mihin.org/fhir/sid/elementId",
            "value": "23642c4b-af78-413f-8a89-6ad32c411aac"
          }
        ],
        "status": "final",
        "category": [
          {
            "coding": [
              {
                "system": "http://hl7.org/fhir/observation-category",
                "code": "vital-signs",
                "display": "Vital Signs"
              }
            ]
          }
        ],
        "code": {
          "coding": [
            {
              "system": "http://loinc.org",
              "code": "8462-4",
              "display": "Diastolic Blood Pressure"
            }
          ]
        },
        "subject": {
          "reference": "Patient/Patient-2646",
          "display": "Lucille Blankenship Holder"
        },
        "context": {
          "reference": "Encounter/Encounter-529",
          "display": "Wellness Visit"
        },
        "effectiveDateTime": "2017-12-01T00:00:00-05:00",
        "performer": [
          {
            "reference": "Practitioner/Practitioner-2573",
            "display": "Leona Delgado Mathews MD"
          }
        ],
        "valueQuantity": {
          "value": 82,
          "unit": "mmHg"
        }
      },
      "request": {
        "method": "PUT",
        "url": "http://localhost:8080/cqf-ruler/baseDstu3/Observation/Observation-65098"
      }
    },
    {
      "fullUrl": "http://localhost:8080/cqf-ruler/baseDstu3/Observation/Observation-65099",
      "resource": {
        "resourceType": "Observation",
        "id": "Observation-65099",
        "meta": {
          "profile": [
            "http://hl7.org/fhir/us/hedis/StructureDefinition/hedis-observation"
          ]
        },
        "extension": [
          {
            "url": "http://mihin.org/extension/copyright",
            "valueString": "Copyright 2014-2019 Michigan Health Information Network Shared Services. Licensed under the Apache License, Version 2.0 (the 'License'); you may not use this file except in compliance with the License. You may obtain a copy of the License at  http://www.apache.org/licenses/LICENSE-2.0.  Unless required by applicable law or agreed to in writing, software distributed under the License is distributed on an 'AS IS' BASIS, WITHOUT WARRANTIES OR CONDITIONS OF ANY KIND, either express or implied. See the License for the specific language governing permissions and limitations under the License."
          }
        ],
        "identifier": [
          {
            "use": "official",
            "system": "mihin.org/fhir/sid/elementId",
            "value": "6af88b01-873b-455f-919b-d7f79868104a"
          }
        ],
        "status": "final",
        "category": [
          {
            "coding": [
              {
                "system": "http://hl7.org/fhir/observation-category",
                "code": "vital-signs",
                "display": "Vital Signs"
              }
            ]
          }
        ],
        "code": {
          "coding": [
            {
              "system": "http://loinc.org",
              "code": "55284-4",
              "display": "Blood Pressure"
            }
          ]
        },
        "subject": {
          "reference": "Patient/Patient-2646",
          "display": "Lucille Blankenship Holder"
        },
        "context": {
          "reference": "Encounter/Encounter-529",
          "display": "Wellness Visit"
        },
        "effectiveDateTime": "2017-12-01T00:00:00-05:00",
        "performer": [
          {
            "reference": "Practitioner/Practitioner-2573",
            "display": "Leona Delgado Mathews MD"
          }
        ]
      },
      "request": {
        "method": "PUT",
        "url": "http://localhost:8080/cqf-ruler/baseDstu3/Observation/Observation-65099"
      }
    }
  ]
}