{
  "resourceType": "Bundle",
  "id": "Janice-Briggs-Moyer-446-Encounter-2375",
  "type": "transaction",
  "entry": [
    {
      "fullUrl": "http://localhost:8080/cqf-ruler/baseDstu3/Encounter/Encounter-2375",
      "resource": {
        "resourceType": "Encounter",
        "id": "Encounter-2375",
        "meta": {
          "profile": [
            "http://hl7.org/fhir/us/hedis/StructureDefinition/hedis-encounter"
          ]
        },
        "extension": [
          {
            "url": "http://mihin.org/extension/copyright",
            "valueString": "Copyright 2014-2018 Michigan Health Information Network Shared Services. Licensed under the Apache License, Version 2.0 (the 'License'); you may not use this file except in compliance with the License. You may obtain a copy of the License at  http://www.apache.org/licenses/LICENSE-2.0.  Unless required by applicable law or agreed to in writing, software distributed under the License is distributed on an 'AS IS' BASIS, WITHOUT WARRANTIES OR CONDITIONS OF ANY KIND, either express or implied. See the License for the specific language governing permissions and limitations under the License."
          }
        ],
        "status": "finished",
        "class": {
          "system": "http://hl7.org/fhir/encounter-class",
          "code": "inpatient",
          "display": "inpatient"
        },
        "type": [
          {
            "coding": [
              {
                "system": "http://snomed.info/sct",
                "code": "32485007",
                "display": "Hospital admission"
              }
            ]
          }
        ],
        "subject": {
          "reference": "Patient/Patient-446",
          "display": "Janice Briggs Moyer"
        },
        "participant": [
          {
            "period": {
              "start": "2018-02-18T00:00:00-05:00",
              "end": "2018-02-18T13:54:00-05:00"
            },
            "individual": {
              "reference": "Practitioner/Practitioner-87",
              "display": "Jerry Clifton Franco MD"
            }
          }
        ],
        "period": {
          "start": "2018-02-18T00:00:00-05:00",
          "end": "2018-02-18T13:54:00-05:00"
        },
        "reason": [
          {
            "coding": [
              {
                "system": "http://snomed.info/sct",
                "code": "68240008",
                "display": "International Federation of Gynecology and Obstetrics cervical cancer stage II (finding) "
              }
            ]
          }
        ],
        "location": [
          {
            "location": {
              "reference": "Location/Location-225",
              "display": "Taylor Methodist Hospital"
            }
          }
        ],
        "serviceProvider": {
          "reference": "Organization/Organization-1024",
          "display": "Taylor Methodist Hospital"
        }
      },
      "request": {
        "method": "PUT",
        "url": "http://localhost:8080/cqf-ruler/baseDstu3/Encounter/Encounter-2375"
      }
    },
    {
      "fullUrl": "http://localhost:8080/cqf-ruler/baseDstu3/Procedure/Procedure-79481",
      "resource": {
        "resourceType": "Procedure",
        "id": "Procedure-79481",
        "meta": {
          "profile": [
            "http://hl7.org/fhir/us/hedis/StructureDefinition/hedis-procedure"
          ]
        },
        "extension": [
          {
            "url": "http://mihin.org/extension/copyright",
            "valueString": "Copyright 2014-2018 Michigan Health Information Network Shared Services. Licensed under the Apache License, Version 2.0 (the 'License'); you may not use this file except in compliance with the License. You may obtain a copy of the License at  http://www.apache.org/licenses/LICENSE-2.0.  Unless required by applicable law or agreed to in writing, software distributed under the License is distributed on an 'AS IS' BASIS, WITHOUT WARRANTIES OR CONDITIONS OF ANY KIND, either express or implied. See the License for the specific language governing permissions and limitations under the License."
          }
        ],
        "identifier": [
          {
            "use": "official",
            "system": "mihin.org/fhir/sid/elementId",
            "value": "b1c54154-c1b2-434b-9dfe-77280ccf4495"
          }
        ],
        "status": "completed",
        "code": {
          "coding": [
            {
              "system": "http://www.ama-assn.org/go/cpt",
              "code": "58954"
            }
          ]
        },
        "subject": {
          "reference": "Patient/Patient-446",
          "display": "Janice Briggs Moyer"
        },
        "context": {
          "reference": "Encounter/Encounter-2375",
          "display": "Cancer_Treatment_Encounter"
        },
        "performedPeriod": {
          "start": "2018-02-18T00:00:00-05:00",
          "end": "2018-02-18T13:54:00-05:00"
        },
        "performer": [
          {
            "actor": {
              "reference": "Practitioner/Practitioner-87",
              "display": "Jerry Clifton Franco MD"
            }
          }
        ],
        "location": {
          "reference": "Location/Location-225",
          "display": "Taylor Methodist Hospital"
        }
      },
      "request": {
        "method": "PUT",
        "url": "http://localhost:8080/cqf-ruler/baseDstu3/Procedure/Procedure-79481"
      }
    }
  ]
}