{
  "resourceType": "Bundle",
  "id": "Don-Travis-Whitaker-Jr-417-Encounter-6850",
  "type": "transaction",
  "entry": [
    {
      "fullUrl": "http://localhost:8080/cqf-ruler/baseDstu3/Encounter/Encounter-6850",
      "resource": {
        "resourceType": "Encounter",
        "id": "Encounter-6850",
        "meta": {
          "profile": [
            "http://hl7.org/fhir/us/hedis/StructureDefinition/hedis-encounter"
          ]
        },
        "extension": [
          {
            "url": "http://mihin.org/extension/copyright",
            "valueString": "Copyright 2014-2018 Michigan Health Information Network Shared Services. Licensed under the Apache License, Version 2.0 (the 'License'); you may not use this file except in compliance with the License. You may obtain a copy of the License at  http://www.apache.org/licenses/LICENSE-2.0.  Unless required by applicable law or agreed to in writing, software distributed under the License is distributed on an 'AS IS' BASIS, WITHOUT WARRANTIES OR CONDITIONS OF ANY KIND, either express or implied. See the License for the specific language governing permissions and limitations under the License."
          }
        ],
        "status": "finished",
        "class": {
          "system": "http://hl7.org/fhir/encounter-class",
          "code": "outpatient",
          "display": "outpatient"
        },
        "type": [
          {
            "coding": [
              {
                "system": "http://snomed.info/sct",
                "code": "185345009",
                "display": "Encounter for symptom"
              }
            ]
          }
        ],
        "subject": {
          "reference": "Patient/Patient-417",
          "display": "Don Travis Whitaker Jr"
        },
        "participant": [
          {
            "period": {
              "start": "2020-11-29T07:00:00-05:00",
              "end": "2020-11-29T07:00:00-05:00"
            },
            "individual": {
              "reference": "Practitioner/Practitioner-403",
              "display": "Doris Linda Frye MD"
            }
          }
        ],
        "period": {
          "start": "2020-11-29T07:00:00-05:00",
          "end": "2020-11-29T07:00:00-05:00"
        },
        "reason": [
          {
            "coding": [
              {
                "system": "http://snomed.info/sct",
                "code": "44054006",
                "display": "Type 2 diabetes mellitus"
              }
            ]
          }
        ],
        "location": [
          {
            "location": {
              "reference": "Location/Location-274",
              "display": "Healthy Living Clinic"
            }
          }
        ],
        "serviceProvider": {
          "reference": "Organization/Organization-1111",
          "display": "Healthy Living Clinic"
        }
      },
      "request": {
        "method": "PUT",
        "url": "http://localhost:8080/cqf-ruler/baseDstu3/Encounter/Encounter-6850"
      }
    },
    {
      "fullUrl": "http://localhost:8080/cqf-ruler/baseDstu3/MedicationRequest/MedicationRequest-184471",
      "resource": {
        "resourceType": "MedicationRequest",
        "id": "MedicationRequest-184471",
        "meta": {
          "profile": [
            "http://hl7.org/fhir/us/hedis/StructureDefinition/hedis-medicationrequest"
          ]
        },
        "extension": [
          {
            "url": "http://mihin.org/extension/copyright",
            "valueString": "Copyright 2014-2018 Michigan Health Information Network Shared Services. Licensed under the Apache License, Version 2.0 (the 'License'); you may not use this file except in compliance with the License. You may obtain a copy of the License at  http://www.apache.org/licenses/LICENSE-2.0.  Unless required by applicable law or agreed to in writing, software distributed under the License is distributed on an 'AS IS' BASIS, WITHOUT WARRANTIES OR CONDITIONS OF ANY KIND, either express or implied. See the License for the specific language governing permissions and limitations under the License."
          }
        ],
        "identifier": [
          {
            "use": "official",
            "system": "mihin.org/fhir/sid/elementId",
            "value": "72ac0d85-822e-4047-bd60-670506445e22"
          }
        ],
        "status": "active",
        "intent": "order",
        "medicationCodeableConcept": {
          "coding": [
            {
              "system": "http://www.nlm.nih.gov/research/umls/rxnorm",
              "code": "106892",
              "display": "insulin human, isophane 70 UNT/ML / Regular Insulin, Human 30 UNT/ML Injectable Suspension [Humulin]"
            }
          ]
        },
        "subject": {
          "reference": "Patient/Patient-417",
          "display": "Don Travis Whitaker Jr"
        },
        "context": {
          "reference": "Encounter/Encounter-6850",
          "display": "Followup_Visit"
        },
        "authoredOn": "2020-11-29T07:00:00-05:00",
        "reasonCode": [
          {
            "coding": [
              {
                "system": "http://snomed.info/sct",
                "code": "44054006",
                "display": "Type 2 diabetes mellitus"
              }
            ]
          }
        ],
        "dosageInstruction": [
          {
            "timing": {
              "repeat": {
                "frequency": 1
              }
            },
            "doseQuantity": {
              "value": 1
            }
          }
        ],
        "dispenseRequest": {
          "validityPeriod": {
            "start": "2020-11-29T07:00:00-05:00",
            "end": "2020-11-29T07:00:00-05:00"
          }
        }
      },
      "request": {
        "method": "PUT",
        "url": "http://localhost:8080/cqf-ruler/baseDstu3/MedicationRequest/MedicationRequest-184471"
      }
    },
    {
      "fullUrl": "http://localhost:8080/cqf-ruler/baseDstu3/MedicationRequest/MedicationRequest-184473",
      "resource": {
        "resourceType": "MedicationRequest",
        "id": "MedicationRequest-184473",
        "meta": {
          "profile": [
            "http://hl7.org/fhir/us/hedis/StructureDefinition/hedis-medicationrequest"
          ]
        },
        "extension": [
          {
            "url": "http://mihin.org/extension/copyright",
            "valueString": "Copyright 2014-2018 Michigan Health Information Network Shared Services. Licensed under the Apache License, Version 2.0 (the 'License'); you may not use this file except in compliance with the License. You may obtain a copy of the License at  http://www.apache.org/licenses/LICENSE-2.0.  Unless required by applicable law or agreed to in writing, software distributed under the License is distributed on an 'AS IS' BASIS, WITHOUT WARRANTIES OR CONDITIONS OF ANY KIND, either express or implied. See the License for the specific language governing permissions and limitations under the License."
          }
        ],
        "identifier": [
          {
            "use": "official",
            "system": "mihin.org/fhir/sid/elementId",
            "value": "a2e5d089-62a3-4960-9a90-bb8e06ababab"
          }
        ],
        "status": "active",
        "intent": "order",
        "medicationCodeableConcept": {
          "coding": [
            {
              "system": "http://www.nlm.nih.gov/research/umls/rxnorm",
              "code": "897122",
              "display": "3 ML liraglutide 6 MG/ML Pen Injector"
            }
          ]
        },
        "subject": {
          "reference": "Patient/Patient-417",
          "display": "Don Travis Whitaker Jr"
        },
        "context": {
          "reference": "Encounter/Encounter-6850",
          "display": "Followup_Visit"
        },
        "authoredOn": "2020-11-29T07:00:00-05:00",
        "reasonCode": [
          {
            "coding": [
              {
                "system": "http://snomed.info/sct",
                "code": "44054006",
                "display": "Type 2 diabetes mellitus"
              }
            ]
          }
        ],
        "dispenseRequest": {
          "validityPeriod": {
            "start": "2020-11-29T07:00:00-05:00",
            "end": "2020-11-29T07:00:00-05:00"
          }
        }
      },
      "request": {
        "method": "PUT",
        "url": "http://localhost:8080/cqf-ruler/baseDstu3/MedicationRequest/MedicationRequest-184473"
      }
    }
  ]
}